<annotation>
	<folder></folder>
	<filename>ezgif-frame-062_jpg.rf.fb575582601042736a21d4631f85204c.jpg</filename>
	<path>ezgif-frame-062_jpg.rf.fb575582601042736a21d4631f85204c.jpg</path>
	<source>
		<database>roboflow.com</database>
	</source>
	<size>
		<width>1280</width>
		<height>720</height>
		<depth>3</depth>
	</size>
	<segmented>0</segmented>
	<object>
		<name>fire</name>
		<pose>Unspecified</pose>
		<truncated>0</truncated>
		<difficult>0</difficult>
		<occluded>0</occluded>
		<bndbox>
			<xmin>676</xmin>
			<xmax>814</xmax>
			<ymin>465</ymin>
			<ymax>646</ymax>
		</bndbox>
	</object>
	<object>
		<name>fire</name>
		<pose>Unspecified</pose>
		<truncated>0</truncated>
		<difficult>0</difficult>
		<occluded>0</occluded>
		<bndbox>
			<xmin>444</xmin>
			<xmax>556</xmax>
			<ymin>410</ymin>
			<ymax>528</ymax>
		</bndbox>
	</object>
</annotation>
