<annotation>
	<folder></folder>
	<filename>ezgif-frame-071_jpg.rf.b22206aa6c7637ef8a63273c2fed6e38.jpg</filename>
	<path>ezgif-frame-071_jpg.rf.b22206aa6c7637ef8a63273c2fed6e38.jpg</path>
	<source>
		<database>roboflow.com</database>
	</source>
	<size>
		<width>1280</width>
		<height>720</height>
		<depth>3</depth>
	</size>
	<segmented>0</segmented>
	<object>
		<name>fire</name>
		<pose>Unspecified</pose>
		<truncated>0</truncated>
		<difficult>0</difficult>
		<occluded>0</occluded>
		<bndbox>
			<xmin>206</xmin>
			<xmax>834</xmax>
			<ymin>77</ymin>
			<ymax>569</ymax>
		</bndbox>
	</object>
</annotation>
