<annotation>
	<folder></folder>
	<filename>ezgif-frame-144_jpg.rf.deec63c552265bb2b2e18efcb22b455b.jpg</filename>
	<path>ezgif-frame-144_jpg.rf.deec63c552265bb2b2e18efcb22b455b.jpg</path>
	<source>
		<database>roboflow.com</database>
	</source>
	<size>
		<width>1280</width>
		<height>720</height>
		<depth>3</depth>
	</size>
	<segmented>0</segmented>
	<object>
		<name>fire</name>
		<pose>Unspecified</pose>
		<truncated>0</truncated>
		<difficult>0</difficult>
		<occluded>0</occluded>
		<bndbox>
			<xmin>507</xmin>
			<xmax>630</xmax>
			<ymin>112</ymin>
			<ymax>460</ymax>
		</bndbox>
	</object>
	<object>
		<name>fire</name>
		<pose>Unspecified</pose>
		<truncated>0</truncated>
		<difficult>0</difficult>
		<occluded>0</occluded>
		<bndbox>
			<xmin>375</xmin>
			<xmax>506</xmax>
			<ymin>249</ymin>
			<ymax>339</ymax>
		</bndbox>
	</object>
</annotation>
