<annotation>
	<folder></folder>
	<filename>wildfire_1117_jpg.rf.21b58d0d5c2b2bfa447cb413ab64da99.jpg</filename>
	<path>wildfire_1117_jpg.rf.21b58d0d5c2b2bfa447cb413ab64da99.jpg</path>
	<source>
		<database>roboflow.com</database>
	</source>
	<size>
		<width>640</width>
		<height>640</height>
		<depth>3</depth>
	</size>
	<segmented>0</segmented>
	<object>
		<name>fire</name>
		<pose>Unspecified</pose>
		<truncated>0</truncated>
		<difficult>0</difficult>
		<occluded>0</occluded>
		<bndbox>
			<xmin>107</xmin>
			<xmax>188</xmax>
			<ymin>237</ymin>
			<ymax>606</ymax>
		</bndbox>
	</object>
	<object>
		<name>fire</name>
		<pose>Unspecified</pose>
		<truncated>0</truncated>
		<difficult>0</difficult>
		<occluded>0</occluded>
		<bndbox>
			<xmin>232</xmin>
			<xmax>564</xmax>
			<ymin>3</ymin>
			<ymax>536</ymax>
		</bndbox>
	</object>
</annotation>
