<annotation>
	<folder></folder>
	<filename>wildfire_1172_jpg.rf.a2784a24cb92f4765fb73979a753249f.jpg</filename>
	<path>wildfire_1172_jpg.rf.a2784a24cb92f4765fb73979a753249f.jpg</path>
	<source>
		<database>roboflow.com</database>
	</source>
	<size>
		<width>640</width>
		<height>640</height>
		<depth>3</depth>
	</size>
	<segmented>0</segmented>
	<object>
		<name>fire</name>
		<pose>Unspecified</pose>
		<truncated>0</truncated>
		<difficult>0</difficult>
		<occluded>0</occluded>
		<bndbox>
			<xmin>285</xmin>
			<xmax>550</xmax>
			<ymin>394</ymin>
			<ymax>609</ymax>
		</bndbox>
	</object>
	<object>
		<name>smoke</name>
		<pose>Unspecified</pose>
		<truncated>0</truncated>
		<difficult>0</difficult>
		<occluded>0</occluded>
		<bndbox>
			<xmin>2</xmin>
			<xmax>641</xmax>
			<ymin>1</ymin>
			<ymax>569</ymax>
		</bndbox>
	</object>
</annotation>
