<annotation>
	<folder></folder>
	<filename>wildfire_600_jpg.rf.183715f8b1404c7a138e9fe73e5d6e47.jpg</filename>
	<path>wildfire_600_jpg.rf.183715f8b1404c7a138e9fe73e5d6e47.jpg</path>
	<source>
		<database>roboflow.com</database>
	</source>
	<size>
		<width>640</width>
		<height>640</height>
		<depth>3</depth>
	</size>
	<segmented>0</segmented>
	<object>
		<name>fire</name>
		<pose>Unspecified</pose>
		<truncated>0</truncated>
		<difficult>0</difficult>
		<occluded>0</occluded>
		<bndbox>
			<xmin>198</xmin>
			<xmax>250</xmax>
			<ymin>434</ymin>
			<ymax>483</ymax>
		</bndbox>
	</object>
	<object>
		<name>smoke</name>
		<pose>Unspecified</pose>
		<truncated>0</truncated>
		<difficult>0</difficult>
		<occluded>0</occluded>
		<bndbox>
			<xmin>288</xmin>
			<xmax>641</xmax>
			<ymin>1</ymin>
			<ymax>346</ymax>
		</bndbox>
	</object>
</annotation>
